{"_format":"","paths":{"artifacts":"out","build_infos":"out/build-info","sources":"src","tests":"test","scripts":"script","libraries":["lib"]},"files":{"lib/forge-std/src/Base.sol":{"lastModificationDate":1743170801196,"contentHash":"ee13c050b1914464f1d3f90cde90204b","sourceName":"lib/forge-std/src/Base.sol","imports":["lib/forge-std/src/StdStorage.sol","lib/forge-std/src/Vm.sol"],"versionRequirement":">=0.6.2, <0.9.0","artifacts":{"CommonBase":{"0.8.28":{"default":{"path":"Base.sol/CommonBase.json","build_id":"7fc03b67147ed81968ed0652b485a3c3"}}},"ScriptBase":{"0.8.28":{"default":{"path":"Base.sol/ScriptBase.json","build_id":"7fc03b67147ed81968ed0652b485a3c3"}}},"TestBase":{"0.8.28":{"default":{"path":"Base.sol/TestBase.json","build_id":"7fc03b67147ed81968ed0652b485a3c3"}}}},"seenByCompiler":true},"lib/forge-std/src/StdAssertions.sol":{"lastModificationDate":1743170801047,"contentHash":"25b77f9806b64d497b8a46aeb8e5f6f0","sourceName":"lib/forge-std/src/StdAssertions.sol","imports":["lib/forge-std/src/Vm.sol"],"versionRequirement":">=0.6.2, <0.9.0","artifacts":{"StdAssertions":{"0.8.28":{"default":{"path":"StdAssertions.sol/StdAssertions.json","build_id":"7fc03b67147ed81968ed0652b485a3c3"}}}},"seenByCompiler":true},"lib/forge-std/src/StdChains.sol":{"lastModificationDate":1743170801197,"contentHash":"66948cf054cccf8b05793a59bd258451","sourceName":"lib/forge-std/src/StdChains.sol","imports":["lib/forge-std/src/Vm.sol"],"versionRequirement":">=0.6.2, <0.9.0","artifacts":{"StdChains":{"0.8.28":{"default":{"path":"StdChains.sol/StdChains.json","build_id":"7fc03b67147ed81968ed0652b485a3c3"}}}},"seenByCompiler":true},"lib/forge-std/src/StdCheats.sol":{"lastModificationDate":1743170801047,"contentHash":"88408106c41697153142f6a6eeb06728","sourceName":"lib/forge-std/src/StdCheats.sol","imports":["lib/forge-std/src/StdStorage.sol","lib/forge-std/src/Vm.sol","lib/forge-std/src/console.sol","lib/forge-std/src/console2.sol"],"versionRequirement":">=0.6.2, <0.9.0","artifacts":{"StdCheats":{"0.8.28":{"default":{"path":"StdCheats.sol/StdCheats.json","build_id":"7fc03b67147ed81968ed0652b485a3c3"}}},"StdCheatsSafe":{"0.8.28":{"default":{"path":"StdCheats.sol/StdCheatsSafe.json","build_id":"7fc03b67147ed81968ed0652b485a3c3"}}}},"seenByCompiler":true},"lib/forge-std/src/StdError.sol":{"lastModificationDate":1743170801048,"contentHash":"64c896e1276a291776e5ea5aecb3870a","sourceName":"lib/forge-std/src/StdError.sol","imports":[],"versionRequirement":">=0.6.2, <0.9.0","artifacts":{"stdError":{"0.8.28":{"default":{"path":"StdError.sol/stdError.json","build_id":"7fc03b67147ed81968ed0652b485a3c3"}}}},"seenByCompiler":true},"lib/forge-std/src/StdInvariant.sol":{"lastModificationDate":1743170801048,"contentHash":"f16837d0e7cb829544ae1f1319ea7643","sourceName":"lib/forge-std/src/StdInvariant.sol","imports":[],"versionRequirement":">=0.6.2, <0.9.0","artifacts":{"StdInvariant":{"0.8.28":{"default":{"path":"StdInvariant.sol/StdInvariant.json","build_id":"7fc03b67147ed81968ed0652b485a3c3"}}}},"seenByCompiler":true},"lib/forge-std/src/StdJson.sol":{"lastModificationDate":1743170801048,"contentHash":"02209da5708eaee03e24a9c24a687370","sourceName":"lib/forge-std/src/StdJson.sol","imports":["lib/forge-std/src/Vm.sol"],"versionRequirement":">=0.6.0, <0.9.0","artifacts":{"stdJson":{"0.8.28":{"default":{"path":"StdJson.sol/stdJson.json","build_id":"7fc03b67147ed81968ed0652b485a3c3"}}}},"seenByCompiler":true},"lib/forge-std/src/StdMath.sol":{"lastModificationDate":1743170801048,"contentHash":"9da8f453eba6bb98f3d75bc6822bfb29","sourceName":"lib/forge-std/src/StdMath.sol","imports":[],"versionRequirement":">=0.6.2, <0.9.0","artifacts":{"stdMath":{"0.8.28":{"default":{"path":"StdMath.sol/stdMath.json","build_id":"7fc03b67147ed81968ed0652b485a3c3"}}}},"seenByCompiler":true},"lib/forge-std/src/StdStorage.sol":{"lastModificationDate":1743170801048,"contentHash":"ce68f6e336944f16d31351a47d0b19b8","sourceName":"lib/forge-std/src/StdStorage.sol","imports":["lib/forge-std/src/Vm.sol"],"versionRequirement":">=0.6.2, <0.9.0","artifacts":{"stdStorage":{"0.8.28":{"default":{"path":"StdStorage.sol/stdStorage.json","build_id":"7fc03b67147ed81968ed0652b485a3c3"}}},"stdStorageSafe":{"0.8.28":{"default":{"path":"StdStorage.sol/stdStorageSafe.json","build_id":"7fc03b67147ed81968ed0652b485a3c3"}}}},"seenByCompiler":true},"lib/forge-std/src/StdStyle.sol":{"lastModificationDate":1743170801048,"contentHash":"6281165a12aa639705c691fccefd855e","sourceName":"lib/forge-std/src/StdStyle.sol","imports":["lib/forge-std/src/Vm.sol"],"versionRequirement":">=0.4.22, <0.9.0","artifacts":{"StdStyle":{"0.8.28":{"default":{"path":"StdStyle.sol/StdStyle.json","build_id":"7fc03b67147ed81968ed0652b485a3c3"}}}},"seenByCompiler":true},"lib/forge-std/src/StdToml.sol":{"lastModificationDate":1743170801048,"contentHash":"4bce85a4c60f2c073e651ee8140bcb4d","sourceName":"lib/forge-std/src/StdToml.sol","imports":["lib/forge-std/src/Vm.sol"],"versionRequirement":">=0.6.0, <0.9.0","artifacts":{"stdToml":{"0.8.28":{"default":{"path":"StdToml.sol/stdToml.json","build_id":"7fc03b67147ed81968ed0652b485a3c3"}}}},"seenByCompiler":true},"lib/forge-std/src/StdUtils.sol":{"lastModificationDate":1743170801048,"contentHash":"4c104fcdec12d3b28348ff9e32c1e4eb","sourceName":"lib/forge-std/src/StdUtils.sol","imports":["lib/forge-std/src/Vm.sol","lib/forge-std/src/interfaces/IMulticall3.sol"],"versionRequirement":">=0.6.2, <0.9.0","artifacts":{"StdUtils":{"0.8.28":{"default":{"path":"StdUtils.sol/StdUtils.json","build_id":"7fc03b67147ed81968ed0652b485a3c3"}}}},"seenByCompiler":true},"lib/forge-std/src/Test.sol":{"lastModificationDate":1743170801197,"contentHash":"b6f15605355fc8c421fe42a90f94bf32","sourceName":"lib/forge-std/src/Test.sol","imports":["lib/forge-std/src/Base.sol","lib/forge-std/src/StdAssertions.sol","lib/forge-std/src/StdChains.sol","lib/forge-std/src/StdCheats.sol","lib/forge-std/src/StdError.sol","lib/forge-std/src/StdInvariant.sol","lib/forge-std/src/StdJson.sol","lib/forge-std/src/StdMath.sol","lib/forge-std/src/StdStorage.sol","lib/forge-std/src/StdStyle.sol","lib/forge-std/src/StdToml.sol","lib/forge-std/src/StdUtils.sol","lib/forge-std/src/Vm.sol","lib/forge-std/src/console.sol","lib/forge-std/src/console2.sol","lib/forge-std/src/interfaces/IMulticall3.sol","lib/forge-std/src/safeconsole.sol"],"versionRequirement":">=0.6.2, <0.9.0","artifacts":{"Test":{"0.8.28":{"default":{"path":"Test.sol/Test.json","build_id":"7fc03b67147ed81968ed0652b485a3c3"}}}},"seenByCompiler":true},"lib/forge-std/src/Vm.sol":{"lastModificationDate":1743170801198,"contentHash":"96e14164f19bc51b0aff863087896678","sourceName":"lib/forge-std/src/Vm.sol","imports":[],"versionRequirement":">=0.6.2, <0.9.0","artifacts":{"Vm":{"0.8.28":{"default":{"path":"Vm.sol/Vm.json","build_id":"7fc03b67147ed81968ed0652b485a3c3"}}},"VmSafe":{"0.8.28":{"default":{"path":"Vm.sol/VmSafe.json","build_id":"7fc03b67147ed81968ed0652b485a3c3"}}}},"seenByCompiler":true},"lib/forge-std/src/console.sol":{"lastModificationDate":1743170801049,"contentHash":"ce19a9e49945b42118379ff99d853c05","sourceName":"lib/forge-std/src/console.sol","imports":[],"versionRequirement":">=0.4.22, <0.9.0","artifacts":{"console":{"0.8.28":{"default":{"path":"console.sol/console.json","build_id":"7fc03b67147ed81968ed0652b485a3c3"}}}},"seenByCompiler":true},"lib/forge-std/src/console2.sol":{"lastModificationDate":1743170801049,"contentHash":"f65ad21034b111e70fb5342d5771efcd","sourceName":"lib/forge-std/src/console2.sol","imports":["lib/forge-std/src/console.sol"],"versionRequirement":">=0.4.22, <0.9.0","artifacts":{},"seenByCompiler":true},"lib/forge-std/src/interfaces/IMulticall3.sol":{"lastModificationDate":1743170801050,"contentHash":"7b131ca1ca32ef6378b7b9ad5488b901","sourceName":"lib/forge-std/src/interfaces/IMulticall3.sol","imports":[],"versionRequirement":">=0.6.2, <0.9.0","artifacts":{"IMulticall3":{"0.8.28":{"default":{"path":"IMulticall3.sol/IMulticall3.json","build_id":"7fc03b67147ed81968ed0652b485a3c3"}}}},"seenByCompiler":true},"lib/forge-std/src/safeconsole.sol":{"lastModificationDate":1743170801051,"contentHash":"1445aa2f47000e212173e0cefd6c7a77","sourceName":"lib/forge-std/src/safeconsole.sol","imports":[],"versionRequirement":">=0.6.2, <0.9.0","artifacts":{"safeconsole":{"0.8.28":{"default":{"path":"safeconsole.sol/safeconsole.json","build_id":"7fc03b67147ed81968ed0652b485a3c3"}}}},"seenByCompiler":true},"lib/openzeppelin-contracts/contracts/security/ReentrancyGuard.sol":{"lastModificationDate":1743171044859,"contentHash":"1535f8c0c68463f8c1b5239f7584e71f","sourceName":"lib/openzeppelin-contracts/contracts/security/ReentrancyGuard.sol","imports":[],"versionRequirement":"^0.8.0","artifacts":{"ReentrancyGuard":{"0.8.28":{"default":{"path":"ReentrancyGuard.sol/ReentrancyGuard.json","build_id":"7fc03b67147ed81968ed0652b485a3c3"}}}},"seenByCompiler":true},"lib/openzeppelin-contracts/contracts/token/ERC20/ERC20.sol":{"lastModificationDate":1743171044864,"contentHash":"3ae5166c6827a9cf1a7a462d1632b464","sourceName":"lib/openzeppelin-contracts/contracts/token/ERC20/ERC20.sol","imports":["lib/openzeppelin-contracts/contracts/token/ERC20/IERC20.sol","lib/openzeppelin-contracts/contracts/token/ERC20/extensions/IERC20Metadata.sol","lib/openzeppelin-contracts/contracts/utils/Context.sol"],"versionRequirement":"^0.8.0","artifacts":{"ERC20":{"0.8.28":{"default":{"path":"ERC20.sol/ERC20.json","build_id":"7fc03b67147ed81968ed0652b485a3c3"}}}},"seenByCompiler":true},"lib/openzeppelin-contracts/contracts/token/ERC20/IERC20.sol":{"lastModificationDate":1743171044864,"contentHash":"df36f7051335cd1e748b1b6463b7fdd3","sourceName":"lib/openzeppelin-contracts/contracts/token/ERC20/IERC20.sol","imports":[],"versionRequirement":"^0.8.0","artifacts":{"IERC20":{"0.8.28":{"default":{"path":"IERC20.sol/IERC20.json","build_id":"7fc03b67147ed81968ed0652b485a3c3"}}}},"seenByCompiler":true},"lib/openzeppelin-contracts/contracts/token/ERC20/extensions/IERC20Metadata.sol":{"lastModificationDate":1743171044868,"contentHash":"909ab67fc5c25033fe6cd364f8c056f9","sourceName":"lib/openzeppelin-contracts/contracts/token/ERC20/extensions/IERC20Metadata.sol","imports":["lib/openzeppelin-contracts/contracts/token/ERC20/IERC20.sol"],"versionRequirement":"^0.8.0","artifacts":{"IERC20Metadata":{"0.8.28":{"default":{"path":"IERC20Metadata.sol/IERC20Metadata.json","build_id":"7fc03b67147ed81968ed0652b485a3c3"}}}},"seenByCompiler":true},"lib/openzeppelin-contracts/contracts/utils/Context.sol":{"lastModificationDate":1743171044881,"contentHash":"f07feb4a44b1a4872370da5aa70e8e46","sourceName":"lib/openzeppelin-contracts/contracts/utils/Context.sol","imports":[],"versionRequirement":"^0.8.0","artifacts":{"Context":{"0.8.28":{"default":{"path":"Context.sol/Context.json","build_id":"7fc03b67147ed81968ed0652b485a3c3"}}}},"seenByCompiler":true},"src/AuthenticationManager.sol":{"lastModificationDate":1743166858393,"contentHash":"8b041eac673aa718a30aa26f690b169f","sourceName":"src/AuthenticationManager.sol","imports":[],"versionRequirement":"^0.8.19","artifacts":{"AuthenticationManager":{"0.8.28":{"default":{"path":"AuthenticationManager.sol/AuthenticationManager.json","build_id":"7fc03b67147ed81968ed0652b485a3c3"}}}},"seenByCompiler":true},"src/EarnRouter.sol":{"lastModificationDate":1743112320000,"contentHash":"6dc65491e6cae26d7d5c7a33796d525d","sourceName":"src/EarnRouter.sol","imports":[],"versionRequirement":null,"artifacts":{},"seenByCompiler":true},"src/IntentExecutor.sol":{"lastModificationDate":1743207612546,"contentHash":"fc6a5ff66e39e4265217af4e412671de","sourceName":"src/IntentExecutor.sol","imports":["src/lib/UserOperation.sol"],"versionRequirement":"^0.8.19","artifacts":{"IEntryPoint":{"0.8.28":{"default":{"path":"IntentExecutor.sol/IEntryPoint.json","build_id":"7fc03b67147ed81968ed0652b485a3c3"}}},"IntentExecutor":{"0.8.28":{"default":{"path":"IntentExecutor.sol/IntentExecutor.json","build_id":"7fc03b67147ed81968ed0652b485a3c3"}}}},"seenByCompiler":true},"src/IntentRouter.sol":{"lastModificationDate":1743130860373,"contentHash":"2d3cb22f8366666f72f3e2c7240702a9","sourceName":"src/IntentRouter.sol","imports":[],"versionRequirement":"^0.8.19","artifacts":{"IntentRouter":{"0.8.28":{"default":{"path":"IntentRouter.sol/IntentRouter.json","build_id":"7fc03b67147ed81968ed0652b485a3c3"}}}},"seenByCompiler":true},"src/SafeYieldVault.sol":{"lastModificationDate":1743203142355,"contentHash":"9210cbf550b56a680a0c7e78760c9ac0","sourceName":"src/SafeYieldVault.sol","imports":["lib/openzeppelin-contracts/contracts/security/ReentrancyGuard.sol","lib/openzeppelin-contracts/contracts/token/ERC20/IERC20.sol","src/strategies/IYieldStrategy.sol"],"versionRequirement":"^0.8.19","artifacts":{"SafeYieldVault":{"0.8.28":{"default":{"path":"SafeYieldVault.sol/SafeYieldVault.json","build_id":"7fc03b67147ed81968ed0652b485a3c3"}}}},"seenByCompiler":true},"src/SafeYieldWallet.sol":{"lastModificationDate":1743207890730,"contentHash":"253fab6cb7c9dcd256eac70615ccefa9","sourceName":"src/SafeYieldWallet.sol","imports":["src/lib/UserOperation.sol"],"versionRequirement":"^0.8.19","artifacts":{"IAuthenticationManager":{"0.8.28":{"default":{"path":"SafeYieldWallet.sol/IAuthenticationManager.json","build_id":"7fc03b67147ed81968ed0652b485a3c3"}}},"SafeYieldWallet":{"0.8.28":{"default":{"path":"SafeYieldWallet.sol/SafeYieldWallet.json","build_id":"7fc03b67147ed81968ed0652b485a3c3"}}}},"seenByCompiler":true},"src/lib/UserOperation.sol":{"lastModificationDate":1743207945559,"contentHash":"1cd07febc2f84d04c81df2c02abb22ef","sourceName":"src/lib/UserOperation.sol","imports":[],"versionRequirement":"^0.8.19","artifacts":{},"seenByCompiler":true},"src/mocks/MockDepositTarget.sol":{"lastModificationDate":1743208066178,"contentHash":"baa41701ce62b47b205ceab82f280f13","sourceName":"src/mocks/MockDepositTarget.sol","imports":[],"versionRequirement":"^0.8.19","artifacts":{"MockDepositTarget":{"0.8.28":{"default":{"path":"MockDepositTarget.sol/MockDepositTarget.json","build_id":"7fc03b67147ed81968ed0652b485a3c3"}}}},"seenByCompiler":true},"src/mocks/MockERC20.sol":{"lastModificationDate":1743202481199,"contentHash":"7d3714db2201feb00fc18e6ad829cd53","sourceName":"src/mocks/MockERC20.sol","imports":["lib/openzeppelin-contracts/contracts/token/ERC20/ERC20.sol","lib/openzeppelin-contracts/contracts/token/ERC20/IERC20.sol","lib/openzeppelin-contracts/contracts/token/ERC20/extensions/IERC20Metadata.sol","lib/openzeppelin-contracts/contracts/utils/Context.sol"],"versionRequirement":"^0.8.19","artifacts":{"MockERC20":{"0.8.28":{"default":{"path":"MockERC20.sol/MockERC20.json","build_id":"7fc03b67147ed81968ed0652b485a3c3"}}}},"seenByCompiler":true},"src/strategies/FixedRateStrategy.sol":{"lastModificationDate":1743173541323,"contentHash":"5e15b5b83d077e296ee6a169f9822b26","sourceName":"src/strategies/FixedRateStrategy.sol","imports":["src/strategies/IYieldStrategy.sol"],"versionRequirement":"^0.8.19","artifacts":{"FixedRateStrategy":{"0.8.28":{"default":{"path":"FixedRateStrategy.sol/FixedRateStrategy.json","build_id":"7fc03b67147ed81968ed0652b485a3c3"}}}},"seenByCompiler":true},"src/strategies/IYieldStrategy.sol":{"lastModificationDate":1743173522381,"contentHash":"1a770e62bbecc19cbe26ea164d0913a1","sourceName":"src/strategies/IYieldStrategy.sol","imports":[],"versionRequirement":"^0.8.19","artifacts":{"IYieldStrategy":{"0.8.28":{"default":{"path":"IYieldStrategy.sol/IYieldStrategy.json","build_id":"7fc03b67147ed81968ed0652b485a3c3"}}}},"seenByCompiler":true},"test/AuthenticationManager.t.sol":{"lastModificationDate":1743166880872,"contentHash":"bb103bfa7e769415fd3028fba7a64314","sourceName":"test/AuthenticationManager.t.sol","imports":["lib/forge-std/src/Base.sol","lib/forge-std/src/StdAssertions.sol","lib/forge-std/src/StdChains.sol","lib/forge-std/src/StdCheats.sol","lib/forge-std/src/StdError.sol","lib/forge-std/src/StdInvariant.sol","lib/forge-std/src/StdJson.sol","lib/forge-std/src/StdMath.sol","lib/forge-std/src/StdStorage.sol","lib/forge-std/src/StdStyle.sol","lib/forge-std/src/StdToml.sol","lib/forge-std/src/StdUtils.sol","lib/forge-std/src/Test.sol","lib/forge-std/src/Vm.sol","lib/forge-std/src/console.sol","lib/forge-std/src/console2.sol","lib/forge-std/src/interfaces/IMulticall3.sol","lib/forge-std/src/safeconsole.sol","src/AuthenticationManager.sol"],"versionRequirement":"^0.8.19","artifacts":{"AuthenticationManagerTest":{"0.8.28":{"default":{"path":"AuthenticationManager.t.sol/AuthenticationManagerTest.json","build_id":"7fc03b67147ed81968ed0652b485a3c3"}}}},"seenByCompiler":true},"test/EarnRouter.t.sol":{"lastModificationDate":1743112320000,"contentHash":"bd9faee9ee8202ad94a3188e3bf3beb0","sourceName":"test/EarnRouter.t.sol","imports":[],"versionRequirement":null,"artifacts":{},"seenByCompiler":true},"test/IntentExecutor.t.sol":{"lastModificationDate":1743208158266,"contentHash":"08177491384cc0b9b43825c536f993d3","sourceName":"test/IntentExecutor.t.sol","imports":["lib/forge-std/src/Base.sol","lib/forge-std/src/StdAssertions.sol","lib/forge-std/src/StdChains.sol","lib/forge-std/src/StdCheats.sol","lib/forge-std/src/StdError.sol","lib/forge-std/src/StdInvariant.sol","lib/forge-std/src/StdJson.sol","lib/forge-std/src/StdMath.sol","lib/forge-std/src/StdStorage.sol","lib/forge-std/src/StdStyle.sol","lib/forge-std/src/StdToml.sol","lib/forge-std/src/StdUtils.sol","lib/forge-std/src/Test.sol","lib/forge-std/src/Vm.sol","lib/forge-std/src/console.sol","lib/forge-std/src/console2.sol","lib/forge-std/src/interfaces/IMulticall3.sol","lib/forge-std/src/safeconsole.sol","lib/openzeppelin-contracts/contracts/token/ERC20/ERC20.sol","lib/openzeppelin-contracts/contracts/token/ERC20/IERC20.sol","lib/openzeppelin-contracts/contracts/token/ERC20/extensions/IERC20Metadata.sol","lib/openzeppelin-contracts/contracts/utils/Context.sol","src/AuthenticationManager.sol","src/IntentExecutor.sol","src/SafeYieldWallet.sol","src/lib/UserOperation.sol","src/mocks/MockDepositTarget.sol","src/mocks/MockERC20.sol"],"versionRequirement":"^0.8.19","artifacts":{"IntentExecutorTest":{"0.8.28":{"default":{"path":"IntentExecutor.t.sol/IntentExecutorTest.json","build_id":"7fc03b67147ed81968ed0652b485a3c3"}}}},"seenByCompiler":true},"test/IntentRouter.t.sol":{"lastModificationDate":1743131017889,"contentHash":"21587cd4397d766e62f9b33c99a3b7a2","sourceName":"test/IntentRouter.t.sol","imports":["lib/forge-std/src/Base.sol","lib/forge-std/src/StdAssertions.sol","lib/forge-std/src/StdChains.sol","lib/forge-std/src/StdCheats.sol","lib/forge-std/src/StdError.sol","lib/forge-std/src/StdInvariant.sol","lib/forge-std/src/StdJson.sol","lib/forge-std/src/StdMath.sol","lib/forge-std/src/StdStorage.sol","lib/forge-std/src/StdStyle.sol","lib/forge-std/src/StdToml.sol","lib/forge-std/src/StdUtils.sol","lib/forge-std/src/Test.sol","lib/forge-std/src/Vm.sol","lib/forge-std/src/console.sol","lib/forge-std/src/console2.sol","lib/forge-std/src/interfaces/IMulticall3.sol","lib/forge-std/src/safeconsole.sol","src/IntentRouter.sol"],"versionRequirement":"^0.8.19","artifacts":{"IntentRouterTest":{"0.8.28":{"default":{"path":"IntentRouter.t.sol/IntentRouterTest.json","build_id":"7fc03b67147ed81968ed0652b485a3c3"}}}},"seenByCompiler":true},"test/SafeYieldVault.t.sol":{"lastModificationDate":1743203239792,"contentHash":"7a43aa6e6f3c935241979be951c0aa6e","sourceName":"test/SafeYieldVault.t.sol","imports":["lib/forge-std/src/Base.sol","lib/forge-std/src/StdAssertions.sol","lib/forge-std/src/StdChains.sol","lib/forge-std/src/StdCheats.sol","lib/forge-std/src/StdError.sol","lib/forge-std/src/StdInvariant.sol","lib/forge-std/src/StdJson.sol","lib/forge-std/src/StdMath.sol","lib/forge-std/src/StdStorage.sol","lib/forge-std/src/StdStyle.sol","lib/forge-std/src/StdToml.sol","lib/forge-std/src/StdUtils.sol","lib/forge-std/src/Test.sol","lib/forge-std/src/Vm.sol","lib/forge-std/src/console.sol","lib/forge-std/src/console2.sol","lib/forge-std/src/interfaces/IMulticall3.sol","lib/forge-std/src/safeconsole.sol","lib/openzeppelin-contracts/contracts/security/ReentrancyGuard.sol","lib/openzeppelin-contracts/contracts/token/ERC20/ERC20.sol","lib/openzeppelin-contracts/contracts/token/ERC20/IERC20.sol","lib/openzeppelin-contracts/contracts/token/ERC20/extensions/IERC20Metadata.sol","lib/openzeppelin-contracts/contracts/utils/Context.sol","src/SafeYieldVault.sol","src/mocks/MockERC20.sol","src/strategies/FixedRateStrategy.sol","src/strategies/IYieldStrategy.sol"],"versionRequirement":"^0.8.19","artifacts":{"SafeYieldVaultTest":{"0.8.28":{"default":{"path":"SafeYieldVault.t.sol/SafeYieldVaultTest.json","build_id":"7fc03b67147ed81968ed0652b485a3c3"}}}},"seenByCompiler":true},"test/SafeYieldWallet.t.sol":{"lastModificationDate":1743207898527,"contentHash":"1b66a6def2a1d0a4fffa51cf0fdb4c2b","sourceName":"test/SafeYieldWallet.t.sol","imports":["lib/forge-std/src/Base.sol","lib/forge-std/src/StdAssertions.sol","lib/forge-std/src/StdChains.sol","lib/forge-std/src/StdCheats.sol","lib/forge-std/src/StdError.sol","lib/forge-std/src/StdInvariant.sol","lib/forge-std/src/StdJson.sol","lib/forge-std/src/StdMath.sol","lib/forge-std/src/StdStorage.sol","lib/forge-std/src/StdStyle.sol","lib/forge-std/src/StdToml.sol","lib/forge-std/src/StdUtils.sol","lib/forge-std/src/Test.sol","lib/forge-std/src/Vm.sol","lib/forge-std/src/console.sol","lib/forge-std/src/console2.sol","lib/forge-std/src/interfaces/IMulticall3.sol","lib/forge-std/src/safeconsole.sol","src/AuthenticationManager.sol","src/SafeYieldWallet.sol","src/lib/UserOperation.sol"],"versionRequirement":"^0.8.19","artifacts":{"SafeYieldWalletTest":{"0.8.28":{"default":{"path":"SafeYieldWallet.t.sol/SafeYieldWalletTest.json","build_id":"7fc03b67147ed81968ed0652b485a3c3"}}}},"seenByCompiler":true}},"builds":["7fc03b67147ed81968ed0652b485a3c3"],"profiles":{"default":{"solc":{"optimizer":{"enabled":true,"runs":200},"metadata":{"useLiteralContent":false,"bytecodeHash":"ipfs","appendCBOR":true},"outputSelection":{"*":{"*":["abi","evm.bytecode.object","evm.bytecode.sourceMap","evm.bytecode.linkReferences","evm.deployedBytecode.object","evm.deployedBytecode.sourceMap","evm.deployedBytecode.linkReferences","evm.deployedBytecode.immutableReferences","evm.methodIdentifiers","metadata"]}},"evmVersion":"cancun","viaIR":false,"libraries":{}},"vyper":{"evmVersion":"cancun","outputSelection":{"*":{"*":["abi","evm.bytecode","evm.deployedBytecode"]}}}}}}